{
 "info": {
  "video_path": "233.mp4",
  "url": "",
  "class": "Documentary",
  "w": 1280,
  "h": 720,
  "num_frame": 12000,
  "fps": 25
 },
 "caption": "",
 "global": [
  {
   "question": "Do more than 5 people appear in the video?",
   "answer": "Yes."
  },
  {
   "question": "Is this clip cartoon?",
   "answer": "No."
  },
  {
   "question": "Does it happen during day or night?",
   "answer": "Day and night."
  },
  {
   "question": "Is this clip relating to our universe?",
   "answer": "Yes."
  },
  {
   "question": "Do stars appear in the video?",
   "answer": "Yes."
  }
 ],
 "breakpoint": [
  {
   "time": 0,
   "question": "Is it indoor or outdoor?",
   "answer": "Indoor."
  },
  {
   "time": 925,
   "question": "Where is the scene?",
   "answer": "In the universe."
  },
  {
   "time": 1675,
   "question": "Is it day or night?",
   "answer": "Day."
  },
  {
   "time": 2275,
   "question": "Is it bright or dark?",
   "answer": "Dark."
  },
  {
   "time": 2850,
   "question": "What is the clothes color of the person?",
   "answer": "Black."
  },
  {
   "time": 3750,
   "question": "Are there any plants?",
   "answer": "No."
  },
  {
   "time": 4500,
   "question": "Are there any vehicles?",
   "answer": "No."
  },
  {
   "time": 5250,
   "question": "Is the person a man or a woman?",
   "answer": "Man."
  },
  {
   "time": 6000,
   "question": "What is the object?",
   "answer": "The sun."
  },
  {
   "time": 6750,
   "question": "Are there any animals?",
   "answer": "No."
  },
  {
   "time": 7500,
   "question": "What is the background color?",
   "answer": "Orange."
  },
  {
   "time": 8250,
   "question": "What is the clothes color of the person?",
   "answer": "Black."
  },
  {
   "time": 9825,
   "question": "Is it indoor or outdoor?",
   "answer": "In the car."
  },
  {
   "time": 10500,
   "question": "Is it day or night?",
   "answer": "Day."
  },
  {
   "time": 11250,
   "question": "What is the clothes color of the person?",
   "answer": "Red."
  }
 ]
}