{
 "info": {
  "video_path": "75.mp4",
  "url": "",
  "class": "Romance Film",
  "w": 1280,
  "h": 696,
  "num_frame": 11520,
  "fps": 24
 },
 "caption": "Under the candlelight of the night, a man and a woman sit together in chairs. The man engages in conversation with the woman while occasionally taking sips from his glass. Meanwhile, a woman walks through a corridor, holding a candle to light her way. The candle's glow reveals a painting on the wall featuring a nude woman. She proceeds into a room, discovering that the room is on fire. Hurriedly, she wakes up a man who is still sleeping and fetches a basin of water to extinguish the flames. Soon, the room falls into darkness. The man drapes a coat over the woman, and she gazes at the clock on the wall, curling up in her chair.",
 "global": [
  {
   "question": "Does it happen during day or night?",
   "answer": "Night."
  },
  {
   "question": "Are there more then three different backgrounds appearing in the video?",
   "answer": "Yes."
  },
  {
   "question": "Do more than 5 people appear in the video?",
   "answer": "No."
  },
  {
   "question": "On which continent does the story takes place?",
   "answer": "Enrope."
  },
  {
   "question": "Does it happen in the 21 st century?",
   "answer": "No."
  }
 ],
 "breakpoint": [
  {
   "time": 0,
   "question": "Is it day or night?",
   "answer": "Night."
  },
  {
   "time": 720,
   "question": "Is the person a man or a woman?",
   "answer": "Woman."
  },
  {
   "time": 1440,
   "question": "Is it indoor or outdoor?",
   "answer": "Indoor."
  },
  {
   "time": 2160,
   "question": "Where is the man siiting?",
   "answer": "On a couch."
  },
  {
   "time": 2880,
   "question": "Are there any people?",
   "answer": "Yes."
  },
  {
   "time": 3600,
   "question": "Is the person a man or a woman?",
   "answer": "Man."
  },
  {
   "time": 4320,
   "question": "Is it day or night?",
   "answer": "Night."
  },
  {
   "time": 5040,
   "question": "Are there any animals?",
   "answer": "No."
  },
  {
   "time": 5760,
   "question": "Are there any plants?",
   "answer": "No."
  },
  {
   "time": 6480,
   "question": "Where is the scene?",
   "answer": "Indoor."
  },
  {
   "time": 7368,
   "question": "Is the person a man or a woman?",
   "answer": "Woman."
  },
  {
   "time": 7920,
   "question": "What is the woman holding?",
   "answer": "A candel."
  },
  {
   "time": 8640,
   "question": "Is it day or night?",
   "answer": "Night."
  },
  {
   "time": 9360,
   "question": "What is happening?",
   "answer": "Fire breaks out."
  },
  {
   "time": 10080,
   "question": "Is it day or night?",
   "answer": "Night."
  }
 ]
}