{
    "info":
    {
        "video_path": "OKJ-10.mp4",
        "url": "",
        "class": "Adventure Film",
        "w": 1280,
        "h": 720,
        "num_frame": 11250,
        "fps": 25.00
    },
    "caption": "A girl was having an intense conversation with someone who was supposed to take their photo. Many people were working on computers. Inside an airport, the girl and an elderly man were surrounded by a crowd of photographers, and people held up banners to welcome them. On an airplane, a flight attendant handed a magazine to the girl. A woman sat at her office desk, and someone delivered a large portrait to her. Inside an airport, a gigantic creature was walking around. A person was driving a car on the road. A man in a lab coat entered a building and dropped something down the stairs. A huge creature approached. A group of people watched surveillance footage on a computer screen and chatted non-stop.",
    "global":
    [
        {
            "question":"When does the things in the video happens, ancient age, modern age or future?(Does the technology exists on earth?)",
            "answer":"It happens at modern time."
        },
        {
            "question":"Are there more then five different places appear in the video(scene switch doesn't necessarily means a place change)?",
            "answer":"Yes."
        },
        {
            "question":"Is there more than three different characters appear(not including people in the background)?",
            "answer":"Yes."
        },
        {
            "question":"what time does the video take place?(at day time or night time?)",
            "answer":"Mainly at night time."
        },
        {
            "question":"Where does the video take place? Indoors or outdoors?",
            "answer":"Mainly indoors."
        }
    ],
    "breakpoint":
    [
        {
            "time":850, 
            "question":"Is it indoors or outdoors?",
            "answer":"It's indoors."
        },
        {
            "time":1600,
            "question":"Is it at day time or night time?",
            "answer":"It's at day time."
        },
        {
            "time":2250,
            "question":"what's the woman doing?",
            "answer":"She is writing something."
        },
        {
            "time":3000, 
            "question":"Is it indoors or outdoors?",
            "answer":"It's indoors."
        },
        {
            "time":3750,
            "question":"where's the scene?",
            "answer":"In a big garage."
        },
        {
            "time":4600,
            "question":"Is it at day time or night time?",
            "answer":"It's at day time."
        },
        {
            "time":5250,
            "question":"Is it indoors or outdoors?",
            "answer":"It's indoors."
        },
        {
            "time":6000,
            "question":"what's abnormal about the man?",
            "answer":"He can't keep himself in balance. He seems to be drunk."
        },
        {
            "time":6750, 
            "question":"what's in the scene?",
            "answer":"A big hippo-like creature."
        },
        {
            "time":7550,
            "question":"what are they doing?",
            "answer":"They're watching a video together."
        },
        {
            "time":8220,
            "question":"what's the gender of the person in the middle of the scene?",
            "answer":"He's a man."
        },
        {
            "time":8850, 
            "question":"what's the woman's hair color?",
            "answer":"It's pink or purple."
        },
        {
            "time":9750,
            "question":"Is there more than five people?",
            "answer":"No."
        },
        {
            "time":10500, 
            "question":"Is it indoors or outdoors?",
            "answer":"It's indoors."
        },
        {
            "time":10625,
            "question":"Is it at day time or night time?",
            "answer":"It's at night time."
        }
    ]
}