{
    "info":
    {
        "video_path": "STW-2.mp4",
        "url": "",
        "class": "Animation Film",
        "w": 1280,
        "h": 720,
        "num_frame": 11250,
        "fps": 25.00
    },
    "caption": "A person goes to the refrigerator, takes out a few items, and places a pot on the stove. They put the food in the pot and pour a few cups of tea. Then, another woman arrives, and the man and woman share a kiss. A boy comes downstairs and sits at the dining table with a dog. The boy begins eating breakfast. In a field, the boy and the man are harvesting crops. A woman is flying an aircraft over the field. A man and a woman are piloting an unusual-looking flying craft. Another boy arrives beneath this flying craft, and a man approaches, engaging in conversation with them. In the distance, a town appears with airships everywhere. People in the town are engaged in various trades. A man and a boy get into a vehicle. Inside a house, a woman and a man are preparing food.",
    "global":
    [
        {
            "question":"Is it a video based on reality or not?(What is the style of the movie?Does it look like cartoon movie?)",
            "answer":"No. It seems like a cartoon movie."
        },
        {
            "question":"Are there more then three different places appear in the video(scene switch doesn't necessarily means a place change)?",
            "answer":"Yes."
        },
        {
            "question":"Is there more than three different characters appear?",
            "answer":"Yes."
        },
        {
            "question":"what time does the video take place?(at day time or night time?)",
            "answer":"Mainly at day time."
        },
        {
            "question":"Where does the video take place? Indoors or outdoors?",
            "answer":"Mainly outdoors."
        }
    ],
    "breakpoint":
    [
        {
            "time":750, 
            "question":"Is it indoors or outdoors?",
            "answer":"It's indoors."
        },
        {
            "time":1500,
            "question":"what's the boy doing?",
            "answer":"He's having breakfast and talking."
        },
        {
            "time":2250,
            "question":"what's in the middle of the scene?",
            "answer":"A plane flies through a farm."
        },
        {
            "time":3000, 
            "question":"Is it indoors or outdoors?",
            "answer":"It's outdoors."
        },
        {
            "time":3750,
            "question":"How many characters appear in the scene?",
            "answer":"One."
        },
        {
            "time":4500,
            "question":"Is there more than four people?",
            "answer":"No."
        },
        {
            "time":5350,
            "question":"How many characters appear in the scene(negelcting background)?",
            "answer":"Two."
        },
        {
            "time":6000,
            "question":"Is it at daytime or at night time?",
            "answer":"It's at day time."
        },
        {
            "time":6750, 
            "question":"Is it indoors or outdoors?",
            "answer":"It's outdoors."
        },
        {
            "time":7500,
            "question":"Is it indoors or outdoors?",
            "answer":"It's outdoors."
        },
        {
            "time":8225,
            "question":"Is there more than ten people in the scene?",
            "answer":"No."
        },
        {
            "time":9000, 
            "question":"How many characters appear in the scene?(people facing the audience)",
            "answer":"One."
        },
        {
            "time":9750,
            "question":"what's the weather like?",
            "answer":"It's sunny and nice."
        },
        {
            "time":10600, 
            "question":"Is there more than five people?",
            "answer":"No."
        },
        {
            "time":11000,
            "question":"Is there more than three people?",
            "answer":"Yes."
        }
    ]
}